{"id":1,"text":"yeaboi #1","date":"21/6/2020","time":"19:48:9"}
{"id":2,"text":"yeaboi #2","date":"21/6/2020","time":"19:48:9"}
{"id":3,"text":"yeaboi #3","date":"21/6/2020","time":"19:48:9"}
{"id":4,"text":"yeaboi #4","date":"21/6/2020","time":"19:48:9"}
{"id":5,"text":"yeaboi #5","date":"21/6/2020","time":"19:48:9"}
{"id":6,"text":"yeaboi #6","date":"21/6/2020","time":"19:48:9"}
{"id":8,"text":"yeaboi #8","date":"21/6/2020","time":"19:48:9"}
{"id":7,"text":"yeaboi #7","date":"21/6/2020","time":"19:48:9"}
{"id":9,"text":"yeaboi #9","date":"21/6/2020","time":"19:48:9"}
